LICENSE
timesfm/__init__.py
timesfm/configs.py
timesfm/timesfm_2p5/timesfm_2p5_base.py
timesfm/timesfm_2p5/timesfm_2p5_torch.py
timesfm/torch/__init__.py
timesfm/torch/dense.py
timesfm/torch/normalization.py
timesfm/torch/transformer.py
timesfm/torch/util.py
v1/LICENSE
timesfm_v1/__init__.py
timesfm_v1/data_loader.py
timesfm_v1/patched_decoder.py
timesfm_v1/pytorch_patched_decoder.py
timesfm_v1/time_features.py
timesfm_v1/timesfm_base.py
timesfm_v1/timesfm_jax.py
timesfm_v1/timesfm_torch.py
timesfm_v1/xreg_lib.py
timecopilot_timesfm-0.2.0.dist-info/METADATA
timecopilot_timesfm-0.2.0.dist-info/WHEEL
timecopilot_timesfm-0.2.0.dist-info/licenses/LICENSE
timecopilot_timesfm-0.2.0.dist-info/RECORD
