Metadata-Version: 2.4
Name: timecopilot-timesfm
Version: 0.2.0
Summary: Open weights time-series foundation model from Google Research.
Project-URL: Homepage, https://github.com/google-research/timesfm
Project-URL: Repository, https://github.com/google-research/timesfm
License-File: LICENSE
Keywords: forecast,time series,time series model,timesfm
Classifier: Environment :: Console
Classifier: Framework :: Flake8
Classifier: Operating System :: OS Independent
Classifier: Topic :: Software Development :: Documentation
Classifier: Topic :: Software Development :: Libraries :: Python Modules
Classifier: Topic :: Software Development :: Quality Assurance
Requires-Python: >=3.10
Requires-Dist: absl-py>=1.4.0
Requires-Dist: einshape>=1.0.0
Requires-Dist: huggingface-hub[cli]>=0.23.0
Requires-Dist: numpy>=1.26.4
Requires-Dist: pandas>=2.0.0
Requires-Dist: safetensors<0.6,>=0.5.3
Requires-Dist: scikit-learn>=1.2.2
Requires-Dist: torch>=2.0.0
Requires-Dist: typer>=0.12.3
Requires-Dist: utilsforecast>=0.1.10
Requires-Dist: wandb>=0.17.5
Provides-Extra: pax
Requires-Dist: jax[cuda12]>=0.4.26; (python_version >= '3.10') and extra == 'pax'
Requires-Dist: jaxlib>=0.4.26; (python_version >= '3.10') and extra == 'pax'
Requires-Dist: lingvo>=0.12.7; (python_version >= '3.10') and extra == 'pax'
Requires-Dist: paxml>=1.4.0; (python_version >= '3.10') and extra == 'pax'
